MexcClient/Enums/__init__.py
MexcClient/Enums/enums.py
MexcClient/Utils/Signature/__init__.py
MexcClient/Utils/Signature/signature.py
MexcClient/Utils/Signature/test_signature.py
MexcClient/Utils/__init__.py
MexcClient/__init__.py
MexcClient/client.py
mexcapiclient-0.1.9.dist-info/WHEEL
mexcapiclient-0.1.9.dist-info/METADATA
mexcapiclient-0.1.9.dist-info/RECORD
