Metadata-Version: 2.1
Name: mexcapiclient
Version: 0.1.9
Summary: 
Home-page: https://github.com/suportebeloj/client-mexc-exchange
License: MIT
Author: Carlos Eduardo
Author-email: suportebeloj@gmail.com
Requires-Python: >=3.8,<4.0
Classifier: License :: OSI Approved :: MIT License
Classifier: Programming Language :: Python :: 3
Classifier: Programming Language :: Python :: 3.8
Classifier: Programming Language :: Python :: 3.9
Classifier: Programming Language :: Python :: 3.10
Classifier: Programming Language :: Python :: 3.11
Requires-Dist: requests (>=2.28.1,<3.0.0)
Project-URL: Repository, https://github.com/suportebeloj/client-mexc-exchange
